renity/__init__.py
renity/__main__.py
renity/constants.py
renity/decoder/__init__.py
renity/decoder/decoder.py
renity/decoder/exceptions.py
renity/encoder/__init__.py
renity/encoder/encoder.py
renity/fields/__init__.py
renity/fields/constants.py
renity/fields/fields.py
renity/fields/interface.py
renity/messages/__init__.py
renity/messages/interface.py
renity/messages/message.py
renity/py.typed
renity/serializers/__init__.py
renity/serializers/interface.py
renity/serializers/serializers.py
renity/utils.py
renity/validators/__init__.py
renity/validators/exceptions.py
renity/validators/interface.py
renity/validators/validators.py
renity-2.1.0.dist-info/LICENSE
renity-2.1.0.dist-info/METADATA
renity-2.1.0.dist-info/WHEEL
renity-2.1.0.dist-info/entry_points.txt
renity-2.1.0.dist-info/RECORD
