Metadata-Version: 2.1
Name: renity
Version: 2.1.0
Summary: Renity Pure Python Protocol Buffer
Home-page: https://github.com/DmitrievichLevin/Renity
License: Apache 2.0
Author: Jalin Howard
Author-email: jhowar39@emich.edu
Requires-Python: >=3.8,<4.0
Classifier: Development Status :: 4 - Beta
Classifier: License :: Other/Proprietary License
Classifier: Programming Language :: Python :: 3
Classifier: Programming Language :: Python :: 3.8
Classifier: Programming Language :: Python :: 3.9
Classifier: Programming Language :: Python :: 3.10
Classifier: Programming Language :: Python :: 3.11
Classifier: Programming Language :: Python :: 3.12
Requires-Dist: bitstring (>=4.1.4)
Requires-Dist: click (>=8.0.1)
Requires-Dist: freezegun (>=1.4.0,<2.0.0)
Requires-Dist: sphinx (>=6.0.0,<7.0.0)
Requires-Dist: typeguard (>=4.1.5,<5.0.0)
Project-URL: Changelog, https://github.com/DmitrievichLevin/Renity/releases
Project-URL: Documentation, https://Renity.readthedocs.io
Project-URL: Repository, https://github.com/DmitrievichLevin/Renity
